mypackagedorachua/__init__.py
mypackagedorachua/mywebcam.py
mypackagedorachua/mywebcam2.py
mypackagedorachua-0.0.8.dist-info/LICENSE
mypackagedorachua-0.0.8.dist-info/METADATA
mypackagedorachua-0.0.8.dist-info/WHEEL
mypackagedorachua-0.0.8.dist-info/top_level.txt
mypackagedorachua-0.0.8.dist-info/RECORD
