Metadata-Version: 2.1
Name: mypackagedorachua
Version: 0.0.8
Summary: A small example package
Home-page: https://github.com/pypa/sampleproject
Author: Dora Chua
Author-email: msdorachua@gmail.com
License: UNKNOWN
Platform: UNKNOWN
Classifier: Programming Language :: Python :: 3
Classifier: License :: OSI Approved :: MIT License
Classifier: Operating System :: OS Independent
Requires-Python: >=3.6
Requires-Dist: opencv-python (>=4.2)
